LICENSE
MANIFEST.in
README.md
pytest_catch_server.py
setup.py
pytest_catch_server.egg-info/PKG-INFO
pytest_catch_server.egg-info/SOURCES.txt
pytest_catch_server.egg-info/dependency_links.txt
pytest_catch_server.egg-info/entry_points.txt
pytest_catch_server.egg-info/requires.txt
pytest_catch_server.egg-info/top_level.txt