Metadata-Version: 2.1
Name: pytest-catch-server
Version: 1.0.0
Summary: Pytest plugin with server for catching HTTP requests.
Home-page: https://github.com/kiwicom/pytest-catch-server
Author: Jan Bednařík
Author-email: jan.bednarik@gmail.com
Maintainer: Jan Bednařík
Maintainer-email: jan.bednarik@gmail.com
License: MIT
Platform: UNKNOWN
Classifier: Development Status :: 5 - Production/Stable
Classifier: Framework :: Pytest
Classifier: Intended Audience :: Developers
Classifier: Topic :: Software Development :: Testing
Classifier: Programming Language :: Python
Classifier: Programming Language :: Python :: 3
Classifier: Programming Language :: Python :: 3.4
Classifier: Programming Language :: Python :: 3.5
Classifier: Programming Language :: Python :: 3.6
Classifier: Programming Language :: Python :: 3.7
Classifier: Programming Language :: Python :: 3.8
Classifier: Programming Language :: Python :: Implementation :: CPython
Classifier: Operating System :: OS Independent
Classifier: License :: OSI Approved :: MIT License
Requires-Python: >=3.4
